piah/__about__.py
piah/__init__.py
piah/_ai.py
piah/_utils.py
piah/parser.py
piah/py.typed
piah-0.1.1.dist-info/METADATA
piah-0.1.1.dist-info/WHEEL
piah-0.1.1.dist-info/licenses/LICENSE.txt
piah-0.1.1.dist-info/RECORD
