Metadata-Version: 2.3
Name: piah
Version: 0.1.1
Summary: automatically parse PDF's and texts to dataclasses
Project-URL: Documentation, https://github.com/fabiobarkoski/piah#readme
Project-URL: Issues, https://github.com/fabiobarkoski/piah/issues
Project-URL: Source, https://github.com/fabiobarkoski/piah
Author-email: fabiobarkoski <fabiobarkoskii@gmail.com>
License-Expression: MIT
License-File: LICENSE.txt
Keywords: ai,dataclass,parser,piah
Classifier: Development Status :: 4 - Beta
Classifier: Programming Language :: Python
Classifier: Programming Language :: Python :: 3.10
Classifier: Programming Language :: Python :: 3.11
Classifier: Programming Language :: Python :: 3.12
Classifier: Programming Language :: Python :: Implementation :: CPython
Classifier: Programming Language :: Python :: Implementation :: PyPy
Requires-Python: >=3.10
Requires-Dist: litellm
Requires-Dist: pypdf
Requires-Dist: python-dotenv
Requires-Dist: setuptools
Requires-Dist: structlog
Requires-Dist: tiktoken
Provides-Extra: dev
Requires-Dist: pre-commit; extra == 'dev'
Requires-Dist: pytest; extra == 'dev'
Requires-Dist: pytest-cov; extra == 'dev'
